afile/__init__.py
afile/command.py
ahash/__init__.py
ahash/command.py
anet/__init__.py
anet/command.py
bhh-0.5.0.dist-info/licenses/LICENSE.txt
bhh-0.5.0.dist-info/METADATA
bhh-0.5.0.dist-info/WHEEL
bhh-0.5.0.dist-info/top_level.txt
bhh-0.5.0.dist-info/RECORD
