Metadata-Version: 2.4
Name: bhh
Version: 0.5.0
Summary: BHH
Author: Aria
Author-email: aria.karami94713@gmail.com
License: BHAP
License-File: LICENSE.txt
Requires-Dist: requests>=2.0.0
Requires-Dist: Pillow>=10.0.0
Dynamic: author
Dynamic: author-email
Dynamic: description
Dynamic: description-content-type
Dynamic: license
Dynamic: license-file
Dynamic: requires-dist
Dynamic: summary
